pyness/__init__.py
pyness/bar.py
pyness/convert.py
pyness/fps.py
pyness/getfileformat.py
pyness/key.py
pyness/runtime.py
pyness/update.py
pyness-1.3.7.dist-info/LICENSE
pyness-1.3.7.dist-info/METADATA
pyness-1.3.7.dist-info/WHEEL
pyness-1.3.7.dist-info/top_level.txt
pyness-1.3.7.dist-info/RECORD
