Metadata-Version: 2.1
Name: pyness
Version: 1.3.7
Summary: Tool for quick necessary stuff
Home-page: https://github.com/BDjisan/pyness.git
Author: BD_jisan
Author-email: islamjisan47@gmail.com
Project-URL: Bug Tracker, https://github.com/BDjisan/pyness/issues
Classifier: Programming Language :: Python :: 3
Classifier: License :: OSI Approved :: MIT License
Classifier: Operating System :: OS Independent
Requires-Python: >=3.5
License-File: LICENSE
